<?xml version="1.0" encoding="utf-8"?>
<Students>
  <StudentIndo>
    <FirstName>Дмитрий</FirstName>
    <LastName>Белов</LastName>
    <University>СФУ</University>
    <Age>18</Age>
    <Course>1</Course>
    <City>Красноярск</City>
  </StudentIndo>
  <StudentIndo>
    <FirstName>Геннадий</FirstName>
    <LastName>Зангиев</LastName>
    <University>СПбГУКА</University>
    <Age>19</Age>
    <Course>2</Course>
    <City>Санкт-Петербург</City>
  </StudentIndo>
  <StudentIndo>
    <FirstName>Николай</FirstName>
    <LastName>Сергеев</LastName>
    <University>БНТУ</University>
    <Age>20</Age>
    <Course>3</Course>
    <City>Минск</City>
  </StudentIndo>
  <StudentIndo>
    <FirstName>Василий</FirstName>
    <LastName>Клецкин</LastName>
    <University>МГУ</University>
    <Age>21</Age>
    <Course>3</Course>
    <City>Москва</City>
  </StudentIndo>
  <StudentIndo>
    <FirstName>Елена</FirstName>
    <LastName>Пирожкова</LastName>
    <University>ИТБИД</University>
    <Age>18</Age>
    <Course>1</Course>
    <City>Санкт-Петербург</City>
  </StudentIndo>
  <StudentIndo>
    <FirstName>Фекла</FirstName>
    <LastName>Борщева</LastName>
    <University>БНТУ</University>
    <Age>22</Age>
    <Course>5</Course>
    <City>Минск</City>
  </StudentIndo>
  <StudentIndo>
    <FirstName>Мария</FirstName>
    <LastName>Вовненко</LastName>
    <University>МГУ</University>
    <Age>23</Age>
    <Course>6</Course>
    <City>Москва</City>
  </StudentIndo>
  <StudentIndo>
    <FirstName>Казенбэк</FirstName>
    <LastName>Югр</LastName>
    <University>МФТИ</University>
    <Age>22</Age>
    <Course>5</Course>
    <City>Москва</City>
  </StudentIndo>
  <StudentIndo>
    <FirstName>Гришко</FirstName>
    <LastName>Грэк</LastName>
    <University>МГУ</University>
    <Age>22</Age>
    <Course>5</Course>
    <City>Москва</City>
  </StudentIndo>
  <StudentIndo>
    <FirstName>Кирилл</FirstName>
    <LastName>Попкадзе</LastName>
    <University>ГАИ</University>
    <Age>19</Age>
    <Course>1</Course>
    <City>Екатеринбург</City>
  </StudentIndo>
  <StudentIndo>
    <FirstName>Сергей</FirstName>
    <LastName>Триланцев</LastName>
    <University>ТРУИ</University>
    <Age>20</Age>
    <Course>2</Course>
    <City>Красноярск</City>
  </StudentIndo>
</Students>